{
	"pages": [ //pages数组中第一项表示应用启动页，参考：https://uniapp.dcloud.io/collocation/pages
		{
			"path": "pages/index/index",
			"style": {
				"navigationBarTitleText": "首页"
			}
		},{
			"path": "pages/set/set",
			"style": {
				"navigationBarTitleText": "设置"
			}
		},{
			"path": "pages/order/order",
			"style": {
				"navigationBarTitleText": "我的订单",
				"app-plus": {
					"bounce": "none"
				}
			}
		},{
		    "path" : "pages/product/list",
		    "style" : {
				"enablePullDownRefresh": true,
				"navigationBarTitleText": "商品列表"
			}
		},{
			"path": "pages/user/user",
			"style": {
				"navigationBarTitleText": "用户中心"
			}
		},{
			"path": "pages/money/pay",
			"style": {
				"navigationBarTitleText": "支付"
			}
		},
		{
			"path": "pages/money/paySuccess",
			"style": {
				"navigationBarTitleText": "支付成功"
			}
		},{
			"path": "pages/address/address",
			"style": {
				"navigationBarTitleText": "收货地址"
			}
		}, {
			"path": "pages/address/addressManage",
			"style": {
				"navigationBarTitleText": ""
			}
		},{
			"path":"pages/order/createOrder",
			"style" : {
				"navigationBarTitleText": "创建订单"
			}
		},{
			"path": "pages/product/product",
			"style": {
				"navigationBarTitleText": "详情展示",
				"app-plus": {
					"titleNView": {
						"type": "transparent"
					}
				}
			}
		},
		{
			"path": "pages/cart/cart",
			"style": {
				"navigationBarTitleText": "购物车"
			}
		},
		{
			"path": "pages/commodity/commodity",
			"style": {
				"navigationBarTitleText": "商品分类"
			}
		}
	],
	"globalStyle": {
		"navigationBarTextStyle": "black",
		"navigationBarTitleText": "uni-app",
		"navigationBarBackgroundColor": "#F8F8F8",
		"backgroundColor": "#F8F8F8"
	},
	"tabBar": {
		"color": "#C0C4CC",
		"selectedColor": "#fa436a",
		"borderStyle": "black",
		"backgroundColor": "#ffffff",
		"list": [{
				"pagePath": "pages/index/index",
				"iconPath": "static/tab-home.png",
				"selectedIconPath": "static/tab-home-current.png",
				"text": "首页"
			},
			{
				"pagePath": "pages/commodity/commodity",
				"iconPath": "static/tab-commodity.png",
				"selectedIconPath": "static/tab-commodity-current.png",
				"text": "商品"
			},
			{
				"pagePath": "pages/order/order",
				"iconPath": "static/tab-order.png",
				"selectedIconPath": "static/tab-order-current.png",
				"text": "订单"
			},
			{
				"pagePath": "pages/cart/cart",
				"iconPath": "static/tab-cart.png",
				"selectedIconPath": "static/tab-cart-current.png",
				"text": "购物车"
			},
			{
				"pagePath": "pages/user/user",
				"iconPath": "static/tab-my.png",
				"selectedIconPath": "static/tab-my-current.png",
				"text": "我的"
			}
		]
	}
}
